{
  "builtAt": "2026-07-23T04:15:39.266Z",
  "builtBy": "local",
  "commit": null,
  "sources": {
    "calendar": {
      "ok": true,
      "fetchedAt": "2026-07-23T04:15:39.266Z",
      "rounds": 22
    },
    "standings": {
      "ok": true,
      "fetchedAt": "2026-07-23T04:15:39.266Z",
      "throughRound": 10
    },
    "markets": {
      "ok": true,
      "fetchedAt": "2026-07-23T04:15:39.266Z",
      "runners": 22
    },
    "weather": {
      "ok": true,
      "fetchedAt": "2026-07-23T04:15:39.266Z",
      "circuit": "Hungaroring"
    },
    "results": {
      "ok": true,
      "fetchedAt": "2026-07-23T04:15:39.266Z",
      "rounds": 10
    },
    "assets": {
      "ok": true,
      "fetchedAt": "2026-07-23T04:15:39.266Z",
      "assets": 33,
      "rounds": 10
    },
    "backtest": {
      "ok": true,
      "fetchedAt": "2026-07-23T04:15:39.266Z",
      "rounds": 7
    }
  },
  "errors": [],
  "staleAfterHours": 36
}
